tracers/__init__.py
tracers/analyzers.py
tracers/config.py
tracers/constants.py
tracers/containers.py
tracers/contextvars.py
tracers/daemon.py
tracers/function/__init__.py
tracers/graphql.py
tracers/py.typed
tracers/utils.py
tracers-21.8.6876.dist-info/WHEEL
tracers-21.8.6876.dist-info/METADATA
tracers-21.8.6876.dist-info/RECORD
