Metadata-Version: 2.1
Name: tracers
Version: 21.8.6876
Summary: Open-Source APM (Application monitoring) project that offers you minimal overhead wrappers for profiling your code execution flow
Home-page: https://github.com/fluidattacks/tracers
License: MIT
Author: Kevin Amado
Author-email: kamadorueda@gmail.com
Requires-Python: >=3.7,<4.0
Classifier: License :: OSI Approved :: MIT License
Classifier: Programming Language :: Python :: 3
Classifier: Programming Language :: Python :: 3.7
Classifier: Programming Language :: Python :: 3.8
Classifier: Programming Language :: Python :: 3.9
Requires-Dist: aioboto3 (==8.0.3)
Requires-Dist: aiogqlc (==1.0.5)
Requires-Dist: more-itertools (==8.4.0)
Project-URL: Repository, https://github.com/fluidattacks/tracers
